emit/__init__.py
emit/constants.py
emit/context.py
emit/log.py
emit/span.py
emit/utils.py
python_emit-0.0.1.dist-info/METADATA
python_emit-0.0.1.dist-info/WHEEL
python_emit-0.0.1.dist-info/top_level.txt
python_emit-0.0.1.dist-info/RECORD
