Metadata-Version: 2.1
Name: python-emit
Version: 0.0.1
Summary: __emit__: all-in-one logging, tracing and auditing
Author-email: Estelle Poulin <dev@inspiredby.es>
License: GPLv3
Project-URL: repository, https://gitlab.com/inspiredbyes/emit
Project-URL: changelog, https://gitlab.com/inspiredbyes/emit/-/blob/main/CHANGELOG.md
Classifier: Programming Language :: Python :: 3
Requires-Python: >=3.11
